md_url_check/__init__.py
md_url_check/__main__.py
md_url_check-0.1.4.dist-info/entry_points.txt
md_url_check-0.1.4.dist-info/WHEEL
md_url_check-0.1.4.dist-info/METADATA
md_url_check-0.1.4.dist-info/RECORD
