Metadata-Version: 2.1
Name: md-url-check
Version: 0.1.4
Summary: Simple CLI tool to check URL health in markdown files.
Home-page: https://github.com/rednafi/md-url-check
License: MIT
Keywords: python,markdown,url,command-line
Author: Redowan Delowar
Author-email: redowan.nafi@gmail.com
Requires-Python: >=3.9,<4.0
Classifier: Environment :: Console
Classifier: License :: OSI Approved :: MIT License
Classifier: Operating System :: OS Independent
Classifier: Programming Language :: Python :: 3
Classifier: Programming Language :: Python :: 3.9
Classifier: Topic :: Software Development
Classifier: Topic :: Software Development :: Libraries :: Python Modules
Classifier: Topic :: Software Development :: Quality Assurance
Project-URL: Repository, https://github.com/rednafi/md-url-check
